ppf/jabref/__init__.py
ppf/jabref/jabref.py
ppf/jabref/utils.py
ppf_jabref-0.1.0.dist-info/LICENSE
ppf_jabref-0.1.0.dist-info/METADATA
ppf_jabref-0.1.0.dist-info/WHEEL
ppf_jabref-0.1.0.dist-info/top_level.txt
ppf_jabref-0.1.0.dist-info/RECORD
